jacc
