Metadata-Version: 2.1
Name: django-jacc
Version: 3.11.12
Summary: Simple double entry accounting system (debits/credits) for Django projects.
Home-page: https://github.com/kajala/django-jacc
Author: Jani Kajala
Author-email: kajala@gmail.com
License: MIT licence, see LICENCE.txt
License-File: LICENSE.txt
